etu_django_frame/__init__.py
etu_django_frame/main.py
etu_django_frame/django/2.2.2/Dockerfile
etu_django_frame/django/2.2.2/README.md
etu_django_frame/django/2.2.2/config_dev
etu_django_frame/django/2.2.2/config_dist
etu_django_frame/django/2.2.2/db.sqlite3
etu_django_frame/django/2.2.2/docker_start.sh
etu_django_frame/django/2.2.2/gitignore
etu_django_frame/django/2.2.2/manage.py
etu_django_frame/django/2.2.2/app/__init__.py
etu_django_frame/django/2.2.2/app/apps.py
etu_django_frame/django/2.2.2/app/tests.py
etu_django_frame/django/2.2.2/app/urls.py
etu_django_frame/django/2.2.2/app/admin/__init__.py
etu_django_frame/django/2.2.2/app/admin/user/__init__.py
etu_django_frame/django/2.2.2/app/admin/user/members_admin.py
etu_django_frame/django/2.2.2/app/migrations/0001_initial.py
etu_django_frame/django/2.2.2/app/migrations/__init__.py
etu_django_frame/django/2.2.2/app/models/__init__.py
etu_django_frame/django/2.2.2/app/models/common/__init__.py
etu_django_frame/django/2.2.2/app/models/common/fake_model.py
etu_django_frame/django/2.2.2/app/models/user/__init__.py
etu_django_frame/django/2.2.2/app/models/user/members.py
etu_django_frame/django/2.2.2/app/serializers/__init__.py
etu_django_frame/django/2.2.2/app/serializers/common/__init__.py
etu_django_frame/django/2.2.2/app/serializers/common/fake_serializer.py
etu_django_frame/django/2.2.2/app/serializers/user/__init__.py
etu_django_frame/django/2.2.2/app/serializers/user/members_serializer.py
etu_django_frame/django/2.2.2/app/tasks/__init__.py
etu_django_frame/django/2.2.2/app/tasks/demo_test.py
etu_django_frame/django/2.2.2/app/views/__init__.py
etu_django_frame/django/2.2.2/app/views/cas_admin/__init__.py
etu_django_frame/django/2.2.2/app/views/cas_admin/views.py
etu_django_frame/django/2.2.2/app/views/comm/__init__.py
etu_django_frame/django/2.2.2/app/views/comm/comm_view.py
etu_django_frame/django/2.2.2/app/views/comm/health_view.py
etu_django_frame/django/2.2.2/app/views/user/__init__.py
etu_django_frame-1.3.6.dist-info/LICENSE
etu_django_frame-1.3.6.dist-info/METADATA
etu_django_frame-1.3.6.dist-info/WHEEL
etu_django_frame-1.3.6.dist-info/entry_points.txt
etu_django_frame-1.3.6.dist-info/top_level.txt
etu_django_frame-1.3.6.dist-info/zip-safe
etu_django_frame-1.3.6.dist-info/RECORD
